.svnignore
.svnkeywords
ChangeLog
INSTALL
LICENSE
README
TODO
bootstrap.py
build.vel
buildout.cfg
epydoc.config
ez_setup.py
googlecode_upload.py
remove.py
setup.cfg
setup.py
update-properties
upload_to_google.sh
examples/boids.py
examples/testboids.py
examples/triangle.png
src/owyl/__init__.py
src/owyl/blackboard.py
src/owyl/core.py
src/owyl/decorators.py
src/owyl/stack.py
src/owyl.egg-info/PKG-INFO
src/owyl.egg-info/SOURCES.txt
src/owyl.egg-info/dependency_links.txt
src/owyl.egg-info/top_level.txt
src/owyl.egg-info/zip-safe
tests/testowyl.py