Metadata-Version: 1.0
Name: owyl
Version: 0.3
Summary: The goal of Owyl: provide a fast and flexible Behavior Tree library implemented in python.
Home-page: http://code.google.com/p/owyl/
Author: David Eyk
Author-email: eykd@eykd.net
License: UNKNOWN
Download-URL: http://code.google.com/p/owyl/downloads/list
Platform: UNKNOWN
Classifier: Development Status :: 3 - Alpha
Classifier: Environment :: Console
Classifier: Intended Audience :: Developers
Classifier: License :: OSI Approved :: BSD License
Classifier: Natural Language :: English
Classifier: Operating System :: OS Independent
Classifier: Programming Language :: Python
Classifier: Topic :: Games/Entertainment
Classifier: Topic :: Scientific/Engineering :: Artificial Intelligence
Classifier: Topic :: Software Development :: Libraries
